simon_trans_database_models/__init__.py
simon_trans_database_models/alembic/__init__.py
simon_trans_database_models/alembic/env.py
simon_trans_database_models/alembic/README
simon_trans_database_models/alembic/script.py.mako
simon_trans_database_models/alembic/versions/014fdfa9a966_add_solar_system_table.py
simon_trans_database_models/alembic/versions/5eee6d4b6713_add_weather_forecast_table.py
simon_trans_database_models/alembic.ini
simon_trans_database_models/tables/__init__.py
simon_trans_database_models/tables/base.py
simon_trans_database_models/tables/solar_system.py
simon_trans_database_models/tables/weather_forecast.py
simon_trans_database_models-0.2.0.dist-info/WHEEL
simon_trans_database_models-0.2.0.dist-info/METADATA
simon_trans_database_models-0.2.0.dist-info/RECORD
