Metadata-Version: 2.1
Name: simon-trans-database-models
Version: 0.2.0
Summary: 
Author: Pintér Tamás
Author-email: tamas.pinter@pannonszoftver.hu
Requires-Python: >=3.8,<4.0
Classifier: Programming Language :: Python :: 3
Classifier: Programming Language :: Python :: 3.10
Classifier: Programming Language :: Python :: 3.8
Classifier: Programming Language :: Python :: 3.9
Requires-Dist: marshmallow (==3.14.1)
Requires-Dist: sqlalchemy (==1.3.18)
